{
  "hipodromo": "VSC",
  "hipodromo_nombre": "Valparaíso Sporting",
  "fecha": "2025-11-02",
  "carreras": [
    {
      "nro_carrera": "1",
      "premio": "\"Hoguera\"\tBolsa de Premios: CLP $1.755.000\t1100m",
      "resultados": [
        {
          "lugar": "1",
          "numero": "3",
          "ejemplar": "Xenotes",
          "padrillo": "Katmai",
          "edad": "",
          "peso_ejemplar": "",
          "distancia": "Haras Matriarca",
          "peso_jinete": "5",
          "jinete": "G. Rodríguez.",
          "preparador": "Braulio Gómez A.",
          "stud": "Tata Gaston",
          "dividendo": "5.5"
        },
        {
          "lugar": "2",
          "numero": "12",
          "ejemplar": "Taisei",
          "padrillo": "Distorted Economy",
          "edad": "",
          "peso_ejemplar": "",
          "distancia": "Haras Lizzie",
          "peso_jinete": "6",
          "jinete": "C. Urbina.",
          "preparador": "Victor Moris L.",
          "stud": "Los Psiquicos",
          "dividendo": "4.7"
        },
        {
          "lugar": "3",
          "numero": "9",
          "ejemplar": "Señora Berni",
          "padrillo": "Good Samaritan",
          "edad": "",
          "peso_ejemplar": "",
          "distancia": "Haras Botafogo",
          "peso_jinete": "4",
          "jinete": "R. Fournet.",
          "preparador": "Victor Moris L.",
          "stud": "Arlequina",
          "dividendo": "11.6"
        },
        {
          "lugar": "4",
          "numero": "6",
          "ejemplar": "Imperadora",
          "padrillo": "Imperia II",
          "edad": "",
          "peso_ejemplar": "",
          "distancia": "Haras Matriarca",
          "peso_jinete": "6",
          "jinete": "J. Miño.",
          "preparador": "William Ara",
          "stud": "William Ara D.",
          "dividendo": "31.3"
        },
        {
          "lugar": "5",
          "numero": "11",
          "ejemplar": "Sueño Del Alma",
          "padrillo": "El Facha",
          "edad": "",
          "peso_ejemplar": "",
          "distancia": "Vicente Meza V.",
          "peso_jinete": "11",
          "jinete": "J. Cueto.",
          "preparador": "Rodrigo Silva. S.",
          "stud": "Rodrigo Silva S.",
          "dividendo": "5.7"
        },
        {
          "lugar": "6",
          "numero": "5",
          "ejemplar": "Germanicus",
          "padrillo": "Midshipman",
          "edad": "",
          "peso_ejemplar": "",
          "distancia": "Haras Don Alberto",
          "peso_jinete": "6",
          "jinete": "P. Reyes.",
          "preparador": "Ximeno Urenda P.",
          "stud": "Don Mario",
          "dividendo": "2.8"
        },
        {
          "lugar": "7",
          "numero": "7",
          "ejemplar": "Loco Hermes",
          "padrillo": "Annual Report",
          "edad": "",
          "peso_ejemplar": "",
          "distancia": "Haras Cordillera",
          "peso_jinete": "4",
          "jinete": "M. Donoso.",
          "preparador": "Rodrigo Silva. S.",
          "stud": "Rodrigo Silva S.",
          "dividendo": "18.4"
        },
        {
          "lugar": "8",
          "numero": "8",
          "ejemplar": "Princesa Ludy",
          "padrillo": "Indian Trail",
          "edad": "",
          "peso_ejemplar": "",
          "distancia": "Ricardo Valverde P.",
          "peso_jinete": "5",
          "jinete": "P. Robles.",
          "preparador": "Victor Moris L.",
          "stud": "Mamita Linda",
          "dividendo": "37.5"
        },
        {
          "lugar": "9",
          "numero": "1",
          "ejemplar": "Pazzelle",
          "padrillo": "Seeking The Dia",
          "edad": "",
          "peso_ejemplar": "",
          "distancia": "Haras Don Alberto",
          "peso_jinete": "6",
          "jinete": "S. González.",
          "preparador": "Victor Caballeria",
          "stud": "Tata Nacho",
          "dividendo": "7.2"
        },
        {
          "lugar": "10",
          "numero": "2",
          "ejemplar": "Bruno Salvaje",
          "padrillo": "Mendelssohn",
          "edad": "",
          "peso_ejemplar": "",
          "distancia": "Haras Don Alberto",
          "peso_jinete": "4",
          "jinete": "G. Pérez.",
          "preparador": "Marcos Contreras",
          "stud": "Guerrero De La Vida",
          "dividendo": "6.3"
        },
        {
          "lugar": "11",
          "numero": "10",
          "ejemplar": "Gran Romano",
          "padrillo": "Constitution",
          "edad": "",
          "peso_ejemplar": "",
          "distancia": "Haras Don Alberto",
          "peso_jinete": "8",
          "jinete": "J. Castillo.",
          "preparador": "Wilfredo Mancilla D.",
          "stud": "Mirafiori",
          "dividendo": "47.2"
        }
      ]
    },
    {
      "nro_carrera": "2",
      "premio": "\"Huingal\"\tBolsa de Premios: CLP $1.890.000\t1100m",
      "resultados": [
        {
          "lugar": "1",
          "numero": "2",
          "ejemplar": "A Tutta Vela",
          "padrillo": "Alfonso",
          "edad": "",
          "peso_ejemplar": "",
          "distancia": "Eduardo Garcia Barrio",
          "peso_jinete": "3",
          "jinete": "J. Herrera.",
          "preparador": "Rafael Bernal T.",
          "stud": "La Reconquista",
          "dividendo": "2.0"
        },
        {
          "lugar": "2",
          "numero": "6",
          "ejemplar": "Cibeles",
          "padrillo": "Seahenge",
          "edad": "",
          "peso_ejemplar": "",
          "distancia": "Abolengo",
          "peso_jinete": "3",
          "jinete": "P. Reyes.",
          "preparador": "Ximeno Urenda P.",
          "stud": "Los Leones",
          "dividendo": "6.1"
        },
        {
          "lugar": "3",
          "numero": "13",
          "ejemplar": "Wannabe",
          "padrillo": "Palm Springs",
          "edad": "",
          "peso_ejemplar": "",
          "distancia": "Haras Doña Icha",
          "peso_jinete": "3",
          "jinete": "G. Pérez.",
          "preparador": "Rafael Bernal T.",
          "stud": "Auguri",
          "dividendo": "2.3"
        },
        {
          "lugar": "4",
          "numero": "12",
          "ejemplar": "Nine Brilliant",
          "padrillo": "Ticket To Run",
          "edad": "",
          "peso_ejemplar": "",
          "distancia": "Haras Matriarca",
          "peso_jinete": "3",
          "jinete": "J. Villagran.",
          "preparador": "Luis Machulas G.",
          "stud": "El Mero Mero",
          "dividendo": "46.3"
        },
        {
          "lugar": "5",
          "numero": "7",
          "ejemplar": "De Bolognia",
          "padrillo": "Viscount Nelson",
          "edad": "",
          "peso_ejemplar": "",
          "distancia": "Haras Don Alberto",
          "peso_jinete": "3",
          "jinete": "G. Rodríguez.",
          "preparador": "Rodrigo Silva. S.",
          "stud": "Rodrigo Silva S.",
          "dividendo": "23.7"
        },
        {
          "lugar": "6",
          "numero": "5",
          "ejemplar": "Candy Dubai",
          "padrillo": "Dubai Sky",
          "edad": "",
          "peso_ejemplar": "",
          "distancia": "Haras Las Araucarias",
          "peso_jinete": "3",
          "jinete": "K. Espina.",
          "preparador": "Cristobal Gonzalez M.",
          "stud": "Charito",
          "dividendo": "8.1"
        },
        {
          "lugar": "7",
          "numero": "10",
          "ejemplar": "Chica Star",
          "padrillo": "International Star",
          "edad": "",
          "peso_ejemplar": "",
          "distancia": "Haras Porta Pía",
          "peso_jinete": "3",
          "jinete": "J. Cueto.",
          "preparador": "Máximo Silva D.",
          "stud": "Hijos Del Rayo",
          "dividendo": "115.4"
        },
        {
          "lugar": "8",
          "numero": "9",
          "ejemplar": "Luna Mezz'o Mare",
          "padrillo": "Lemon Sour",
          "edad": "",
          "peso_ejemplar": "",
          "distancia": "Criadero Ojo Seco",
          "peso_jinete": "3",
          "jinete": "J. Miño.",
          "preparador": "William Ara",
          "stud": "William Ara D.",
          "dividendo": "43.5"
        },
        {
          "lugar": "9",
          "numero": "3",
          "ejemplar": "Sundy Point",
          "padrillo": "The Lumber Guy",
          "edad": "",
          "peso_ejemplar": "",
          "distancia": "Jose Sanchez Cvitanic",
          "peso_jinete": "3",
          "jinete": "C. Urbina.",
          "preparador": "Jorge Araneda M.",
          "stud": "Alma Fueguina",
          "dividendo": "21.6"
        },
        {
          "lugar": "10",
          "numero": "4",
          "ejemplar": "La Propia Hermana",
          "padrillo": "The Lumber Guy",
          "edad": "",
          "peso_ejemplar": "",
          "distancia": "Haras Lizzie",
          "peso_jinete": "3",
          "jinete": "R. Fournet.",
          "preparador": "Braulio Gómez A.",
          "stud": "J.J.",
          "dividendo": "113.0"
        },
        {
          "lugar": "11",
          "numero": "11",
          "ejemplar": "Majnun Amyra",
          "padrillo": "Lemon Sour",
          "edad": "",
          "peso_ejemplar": "",
          "distancia": "Criadero Ojo Seco",
          "peso_jinete": "3",
          "jinete": "M. Donoso.",
          "preparador": "William Ara",
          "stud": "William Ara D.",
          "dividendo": "82.0"
        },
        {
          "lugar": "12",
          "numero": "1",
          "ejemplar": "Kat Dubai",
          "padrillo": "Dubai Sky",
          "edad": "",
          "peso_ejemplar": "",
          "distancia": "Haras Las Araucarias",
          "peso_jinete": "3",
          "jinete": "M. Gutiérrez.",
          "preparador": "Cristobal Gonzalez M.",
          "stud": "Charito",
          "dividendo": "26.8"
        },
        {
          "lugar": "13",
          "numero": "8",
          "ejemplar": "La Mujer De Blanco",
          "padrillo": "Wingman",
          "edad": "",
          "peso_ejemplar": "",
          "distancia": "",
          "peso_jinete": "3",
          "jinete": "W. Quinteros.",
          "preparador": "Eduardo Donoso",
          "stud": "Winman",
          "dividendo": "49.1"
        }
      ]
    },
    {
      "nro_carrera": "3",
      "premio": "\"Heika\"\tBolsa de Premios: CLP $1.957.500\t1100m",
      "resultados": [
        {
          "lugar": "1",
          "numero": "9",
          "ejemplar": "Janstar",
          "padrillo": "International Star",
          "edad": "",
          "peso_ejemplar": "",
          "distancia": "Haras Las Araucarias",
          "peso_jinete": "4",
          "jinete": "C. Urbina.",
          "preparador": "Marcos Contreras",
          "stud": "Guerrero De La Vida",
          "dividendo": "8.7"
        },
        {
          "lugar": "2",
          "numero": "10",
          "ejemplar": "Dentato",
          "padrillo": "Good Samaritan",
          "edad": "",
          "peso_ejemplar": "",
          "distancia": "Haras Melipilla",
          "peso_jinete": "4",
          "jinete": "S. González.",
          "preparador": "Victor Caballeria",
          "stud": "Tata Nacho",
          "dividendo": "2.6"
        },
        {
          "lugar": "3",
          "numero": "6",
          "ejemplar": "Desprolijo",
          "padrillo": "Good Samaritan",
          "edad": "",
          "peso_ejemplar": "",
          "distancia": "Haras Santa Sara",
          "peso_jinete": "5",
          "jinete": "F. Tapia.",
          "preparador": "Carlos Vásquez P.",
          "stud": "Doña Sofía",
          "dividendo": "12.9"
        },
        {
          "lugar": "4",
          "numero": "1",
          "ejemplar": "Gerasimova",
          "padrillo": "Aragorn II",
          "edad": "",
          "peso_ejemplar": "",
          "distancia": "Haras Dadinco",
          "peso_jinete": "5",
          "jinete": "F. Olivares.",
          "preparador": "Marcos Contreras",
          "stud": "Guerrero De La Vida",
          "dividendo": "4.3"
        },
        {
          "lugar": "5",
          "numero": "5",
          "ejemplar": "Conducta Infame",
          "padrillo": "Van Nistelrooy",
          "edad": "",
          "peso_ejemplar": "",
          "distancia": "Haras Dadinco",
          "peso_jinete": "4",
          "jinete": "K. Espina.",
          "preparador": "Wilfredo Mancilla D.",
          "stud": "Wilfredo Mancilla D.",
          "dividendo": "4.7"
        },
        {
          "lugar": "6",
          "numero": "4",
          "ejemplar": "Ciudadano Kane",
          "padrillo": "Mendelssohn",
          "edad": "",
          "peso_ejemplar": "",
          "distancia": "Haras Don Alberto",
          "peso_jinete": "3",
          "jinete": "G. Pérez.",
          "preparador": "Ximeno Urenda P.",
          "stud": "Don Mario",
          "dividendo": "9.6"
        },
        {
          "lugar": "7",
          "numero": "8",
          "ejemplar": "Sweet Sundown",
          "padrillo": "Until Sundown",
          "edad": "",
          "peso_ejemplar": "",
          "distancia": "Juan Diaz Estay",
          "peso_jinete": "4",
          "jinete": "C. Poblete.",
          "preparador": "Guillermo Pérez C.",
          "stud": "El Paso Cabreria",
          "dividendo": "27.2"
        },
        {
          "lugar": "8",
          "numero": "7",
          "ejemplar": "Canela Star",
          "padrillo": "Awesome Patriot",
          "edad": "",
          "peso_ejemplar": "",
          "distancia": "Haras Santa Sara",
          "peso_jinete": "4",
          "jinete": "J. Soto.",
          "preparador": "Victor Caballeria",
          "stud": "Tata Nacho",
          "dividendo": "53.4"
        },
        {
          "lugar": "9",
          "numero": "2",
          "ejemplar": "Alas De Plata",
          "padrillo": "Stay Thirsty",
          "edad": "",
          "peso_ejemplar": "",
          "distancia": "Haras Don Alberto",
          "peso_jinete": "8",
          "jinete": "R. Fuenzalida.",
          "preparador": "Victor Moris L.",
          "stud": "Galiano",
          "dividendo": "28.2"
        },
        {
          "lugar": "10",
          "numero": "3",
          "ejemplar": "Union Army",
          "padrillo": "Il Campione",
          "edad": "",
          "peso_ejemplar": "",
          "distancia": "Santa Inés",
          "peso_jinete": "7",
          "jinete": "G. Rodríguez.",
          "preparador": "Victor Caballeria",
          "stud": "Tata Nacho",
          "dividendo": "4.3"
        }
      ]
    },
    {
      "nro_carrera": "4",
      "premio": "\"Hegemonia\"\tBolsa de Premios: CLP $1.755.000\t1100m",
      "resultados": [
        {
          "lugar": "1",
          "numero": "8",
          "ejemplar": "Muy Avispada",
          "padrillo": "Exaggerator",
          "edad": "",
          "peso_ejemplar": "",
          "distancia": "Haras Doña Icha",
          "peso_jinete": "4",
          "jinete": "A. Alvarez.",
          "preparador": "Braulio Gómez A.",
          "stud": "Amarduq",
          "dividendo": "5.5"
        },
        {
          "lugar": "2",
          "numero": "10",
          "ejemplar": "Caribean Passion",
          "padrillo": "Passion for Gold",
          "edad": "",
          "peso_ejemplar": "",
          "distancia": "Haras Melipilla",
          "peso_jinete": "7",
          "jinete": "F. Olivares.",
          "preparador": "Inés Maffud H.",
          "stud": "Alicahue",
          "dividendo": "4.1"
        },
        {
          "lugar": "3",
          "numero": "4",
          "ejemplar": "Oppa",
          "padrillo": "Sumerio",
          "edad": "",
          "peso_ejemplar": "",
          "distancia": "Haras Santa Mariana",
          "peso_jinete": "4",
          "jinete": "S. González.",
          "preparador": "Luis Catena C.",
          "stud": "Alfombra Magica",
          "dividendo": "5.2"
        },
        {
          "lugar": "4",
          "numero": "2",
          "ejemplar": "Afirmate Gato",
          "padrillo": "Seeking The Dia",
          "edad": "",
          "peso_ejemplar": "",
          "distancia": "Haras Don Alberto",
          "peso_jinete": "6",
          "jinete": "M. Salinas.",
          "preparador": "Juan R. García V.",
          "stud": "Don Salvador",
          "dividendo": "14.0"
        },
        {
          "lugar": "5",
          "numero": "12",
          "ejemplar": "Te Canto A Ti",
          "padrillo": "Gemologist",
          "edad": "",
          "peso_ejemplar": "",
          "distancia": "Haras Santa Olga",
          "peso_jinete": "6",
          "jinete": "P. Reyes.",
          "preparador": "Carlos Vásquez P.",
          "stud": "Doña Sofía",
          "dividendo": "4.5"
        },
        {
          "lugar": "6",
          "numero": "7",
          "ejemplar": "Justinsito Crack",
          "padrillo": "Daddy Long Legs",
          "edad": "",
          "peso_ejemplar": "",
          "distancia": "Haras Santa Olga",
          "peso_jinete": "6",
          "jinete": "J. Cueto.",
          "preparador": "Juan R. García V.",
          "stud": "Juan Garcia V.",
          "dividendo": "44.8"
        },
        {
          "lugar": "7",
          "numero": "11",
          "ejemplar": "Regalito",
          "padrillo": "Viscount Nelson",
          "edad": "",
          "peso_ejemplar": "",
          "distancia": "Haras Don Alberto",
          "peso_jinete": "9",
          "jinete": "G. Rodríguez.",
          "preparador": "Gabriel Reyes I.",
          "stud": "Gabriel Reyes G.",
          "dividendo": "9.8"
        },
        {
          "lugar": "8",
          "numero": "1",
          "ejemplar": "Mipipo",
          "padrillo": "Exaggerator",
          "edad": "",
          "peso_ejemplar": "",
          "distancia": "Haras Doña Icha",
          "peso_jinete": "4",
          "jinete": "G. Pérez.",
          "preparador": "Victor Caballeria",
          "stud": "Nor Sur",
          "dividendo": "26.1"
        },
        {
          "lugar": "9",
          "numero": "6",
          "ejemplar": "El Veneco",
          "padrillo": "Dylan Thomas",
          "edad": "",
          "peso_ejemplar": "",
          "distancia": "Haras Don Alberto",
          "peso_jinete": "5",
          "jinete": "R. Fuenzalida.",
          "preparador": "Victor Caballeria",
          "stud": "Nor Sur",
          "dividendo": "5.0"
        },
        {
          "lugar": "10",
          "numero": "3",
          "ejemplar": "Viva Magenta",
          "padrillo": "Constitution",
          "edad": "",
          "peso_ejemplar": "",
          "distancia": "Haras Don Alberto",
          "peso_jinete": "5",
          "jinete": "J. Miño.",
          "preparador": "William Ara",
          "stud": "William Ara D.",
          "dividendo": "37.8"
        },
        {
          "lugar": "11",
          "numero": "5",
          "ejemplar": "Cala De Oro",
          "padrillo": "Mendelssohn",
          "edad": "",
          "peso_ejemplar": "",
          "distancia": "Haras Don Alberto",
          "peso_jinete": "4",
          "jinete": "K. Espina.",
          "preparador": "Cristobal Gonzalez M.",
          "stud": "Charito",
          "dividendo": "11.5"
        }
      ]
    },
    {
      "nro_carrera": "5",
      "premio": "\"Jaime Munro P.\"\tBolsa de Premios: CLP $3.915.000\t1300m",
      "resultados": [
        {
          "lugar": "1",
          "numero": "10",
          "ejemplar": "Ocho De Abril",
          "padrillo": "Constitution",
          "edad": "",
          "peso_ejemplar": "",
          "distancia": "Haras Don Alberto",
          "peso_jinete": "7",
          "jinete": "J. Medina.",
          "preparador": "Juan Pablo Baeza J.",
          "stud": "Colorado Veintitres",
          "dividendo": "4.8"
        },
        {
          "lugar": "2",
          "numero": "12",
          "ejemplar": "Exhausting",
          "padrillo": "Lookin At Lucky",
          "edad": "",
          "peso_ejemplar": "",
          "distancia": "Haras Don Alberto",
          "peso_jinete": "6",
          "jinete": "W. León.",
          "preparador": "Gonzalo Vegas C.",
          "stud": "Siempre Avante",
          "dividendo": "7.8"
        },
        {
          "lugar": "3",
          "numero": "9",
          "ejemplar": "Blue Label",
          "padrillo": "Mendelssohn",
          "edad": "",
          "peso_ejemplar": "",
          "distancia": "Haras Don Alberto",
          "peso_jinete": "4",
          "jinete": "P. Robles.",
          "preparador": "Victor Moris L.",
          "stud": "JS",
          "dividendo": "20.0"
        },
        {
          "lugar": "4",
          "numero": "3",
          "ejemplar": "Bismark",
          "padrillo": "Equal Stripes",
          "edad": "",
          "peso_ejemplar": "",
          "distancia": "Abolengo",
          "peso_jinete": "4",
          "jinete": "A. Alvarez.",
          "preparador": "Ximeno Urenda P.",
          "stud": "Los Leones",
          "dividendo": "11.3"
        },
        {
          "lugar": "5",
          "numero": "5",
          "ejemplar": "Good Runner",
          "padrillo": "Good Samaritan",
          "edad": "",
          "peso_ejemplar": "",
          "distancia": "Haras Matriarca",
          "peso_jinete": "5",
          "jinete": "G. Pérez.",
          "preparador": "José Araya B.",
          "stud": "Matriarca",
          "dividendo": "7.6"
        },
        {
          "lugar": "6",
          "numero": "6",
          "ejemplar": "Petit Profesor",
          "padrillo": "Midshipman",
          "edad": "",
          "peso_ejemplar": "",
          "distancia": "Haras Don Alberto",
          "peso_jinete": "4",
          "jinete": "J. Herrera.",
          "preparador": "Ximeno Urenda P.",
          "stud": "Don Mario",
          "dividendo": "1.9"
        },
        {
          "lugar": "7",
          "numero": "11",
          "ejemplar": "Black Thunder",
          "padrillo": "Viscount Nelson",
          "edad": "",
          "peso_ejemplar": "",
          "distancia": "Haras Don Alberto",
          "peso_jinete": "6",
          "jinete": "M. Salinas.",
          "preparador": "Ximeno Urenda P.",
          "stud": "Nativo",
          "dividendo": "39.4"
        },
        {
          "lugar": "8",
          "numero": "2",
          "ejemplar": "Cafe Ristretto",
          "padrillo": "Strong Mandate",
          "edad": "",
          "peso_ejemplar": "",
          "distancia": "Haras Doña Icha",
          "peso_jinete": "8",
          "jinete": "K. Espina.",
          "preparador": "Osvaldo Urbina H.",
          "stud": "Kissimmee",
          "dividendo": "7.0"
        },
        {
          "lugar": "9",
          "numero": "4",
          "ejemplar": "Mis Mejores Amigos",
          "padrillo": "War Command",
          "edad": "",
          "peso_ejemplar": "",
          "distancia": "Haras Don Alberto",
          "peso_jinete": "5",
          "jinete": "P. Reyes.",
          "preparador": "Carlos Vásquez P.",
          "stud": "Doña Sofía",
          "dividendo": "11.8"
        },
        {
          "lugar": "10",
          "numero": "8",
          "ejemplar": "Sueño Chilote",
          "padrillo": "Court Vision",
          "edad": "",
          "peso_ejemplar": "",
          "distancia": "Rosa Badaracco C.",
          "peso_jinete": "8",
          "jinete": "F. Tapia.",
          "preparador": "Carlos Vásquez P.",
          "stud": "Doña Sofía",
          "dividendo": "23.0"
        },
        {
          "lugar": "11",
          "numero": "7",
          "ejemplar": "Empezar de Nuevo",
          "padrillo": "Ahora II",
          "edad": "",
          "peso_ejemplar": "",
          "distancia": "Haras Viejo Perro",
          "peso_jinete": "5",
          "jinete": "C. Urbina.",
          "preparador": "Jorge Araneda M.",
          "stud": "Renita",
          "dividendo": "69.2"
        }
      ]
    },
    {
      "nro_carrera": "6",
      "premio": "\"Hilandeira\"\tBolsa de Premios: CLP $2.295.000\t1400m",
      "resultados": [
        {
          "lugar": "1",
          "numero": "4",
          "ejemplar": "Nalhuitad",
          "padrillo": "Flameaway",
          "edad": "",
          "peso_ejemplar": "",
          "distancia": "Haras Candelaria Bío Bío",
          "peso_jinete": "4",
          "jinete": "G. Pérez.",
          "preparador": "José Leiva L.",
          "stud": "Linlinao",
          "dividendo": "6.2"
        },
        {
          "lugar": "2",
          "numero": "6",
          "ejemplar": "Constitution's Son",
          "padrillo": "Constitution",
          "edad": "",
          "peso_ejemplar": "",
          "distancia": "Haras Don Alberto",
          "peso_jinete": "8",
          "jinete": "J. Medina.",
          "preparador": "Carlos Vásquez P.",
          "stud": "Doña Sofía",
          "dividendo": "2.8"
        },
        {
          "lugar": "3",
          "numero": "1",
          "ejemplar": "Ted",
          "padrillo": "Exaggerator",
          "edad": "",
          "peso_ejemplar": "",
          "distancia": "Haras Porta Pía",
          "peso_jinete": "5",
          "jinete": "S. González.",
          "preparador": "Victor Caballeria",
          "stud": "Tata Nacho",
          "dividendo": "6.1"
        },
        {
          "lugar": "4",
          "numero": "7",
          "ejemplar": "Liucura Park",
          "padrillo": "Straight Up",
          "edad": "",
          "peso_ejemplar": "",
          "distancia": "",
          "peso_jinete": "5",
          "jinete": "W. Quinteros.",
          "preparador": "Marcos Contreras",
          "stud": "Guerrero De La Vida",
          "dividendo": "19.0"
        },
        {
          "lugar": "5",
          "numero": "2",
          "ejemplar": "Keidar",
          "padrillo": "Catcher in the Rye",
          "edad": "",
          "peso_ejemplar": "",
          "distancia": "Santa Inés",
          "peso_jinete": "7",
          "jinete": "J. Herrera.",
          "preparador": "Luis Catena C.",
          "stud": "Granadilla",
          "dividendo": "1.9"
        },
        {
          "lugar": "6",
          "numero": "8",
          "ejemplar": "Pablosky",
          "padrillo": "Ascot Prince",
          "edad": "",
          "peso_ejemplar": "",
          "distancia": "Haras Don Luis",
          "peso_jinete": "5",
          "jinete": "G. Rodríguez.",
          "preparador": "Braulio Gómez A.",
          "stud": "Amarduq",
          "dividendo": "11.6"
        },
        {
          "lugar": "7",
          "numero": "3",
          "ejemplar": "Luca Brasi",
          "padrillo": "Ecliptic",
          "edad": "",
          "peso_ejemplar": "",
          "distancia": "Haras Mocito Guapo",
          "peso_jinete": "9",
          "jinete": "F. Tapia.",
          "preparador": "Carlos Vásquez P.",
          "stud": "Doña Sofía",
          "dividendo": "48.6"
        },
        {
          "lugar": "8",
          "numero": "9",
          "ejemplar": "Greenboy",
          "padrillo": "Stevie Wonderboy",
          "edad": "",
          "peso_ejemplar": "",
          "distancia": "Haras Santa Marta",
          "peso_jinete": "9",
          "jinete": "F. Medina.",
          "preparador": "Ramón Olivares",
          "stud": "Periko",
          "dividendo": "24.8"
        }
      ]
    },
    {
      "nro_carrera": "7",
      "premio": "\"High Bridge\"\tBolsa de Premios: CLP $2.025.000\t1100m",
      "resultados": [
        {
          "lugar": "1",
          "numero": "7",
          "ejemplar": "Por Mi Mismo",
          "padrillo": "Gemologist",
          "edad": "",
          "peso_ejemplar": "",
          "distancia": "Haras Santa Olga",
          "peso_jinete": "6",
          "jinete": "K. Espina.",
          "preparador": "Wilfredo Mancilla D.",
          "stud": "Maquehua",
          "dividendo": "4.1"
        },
        {
          "lugar": "2",
          "numero": "5",
          "ejemplar": "Ropopompom",
          "padrillo": "Patternrecognition",
          "edad": "",
          "peso_ejemplar": "",
          "distancia": "Haras Santa Olga",
          "peso_jinete": "4",
          "jinete": "G. Pérez.",
          "preparador": "Juan R. García V.",
          "stud": "Don Salvador",
          "dividendo": "3.4"
        },
        {
          "lugar": "3",
          "numero": "4",
          "ejemplar": "No Me Equivoque",
          "padrillo": "Classic Empire",
          "edad": "",
          "peso_ejemplar": "",
          "distancia": "Haras Paso Nevado",
          "peso_jinete": "4",
          "jinete": "P. Reyes.",
          "preparador": "Carlos Vásquez P.",
          "stud": "Doña Sofía",
          "dividendo": "9.0"
        },
        {
          "lugar": "4",
          "numero": "6",
          "ejemplar": "Kapu",
          "padrillo": "Sumerio",
          "edad": "",
          "peso_ejemplar": "",
          "distancia": "",
          "peso_jinete": "4",
          "jinete": "G. Rodríguez.",
          "preparador": "Gonzalo Vegas C.",
          "stud": "Los Parritas",
          "dividendo": "3.1"
        },
        {
          "lugar": "5",
          "numero": "1",
          "ejemplar": "Il Vento",
          "padrillo": "Exaggerator",
          "edad": "",
          "peso_ejemplar": "",
          "distancia": "Haras Doña Icha",
          "peso_jinete": "5",
          "jinete": "M. Gutiérrez.",
          "preparador": "Máximo Silva D.",
          "stud": "M S D",
          "dividendo": "7.0"
        },
        {
          "lugar": "6",
          "numero": "8",
          "ejemplar": "Indian Melody",
          "padrillo": "Indian Trail",
          "edad": "",
          "peso_ejemplar": "",
          "distancia": "Haras Sumaya",
          "peso_jinete": "3",
          "jinete": "J. Castillo.",
          "preparador": "Wilfredo Mancilla D.",
          "stud": "French Potato",
          "dividendo": "3.6"
        }
      ]
    },
    {
      "nro_carrera": "8",
      "premio": "\"Hunter Special\"\tBolsa de Premios: CLP $1.822.500\t1100m",
      "resultados": [
        {
          "lugar": "1",
          "numero": "14",
          "ejemplar": "Medford",
          "padrillo": "Mendelssohn",
          "edad": "",
          "peso_ejemplar": "",
          "distancia": "Haras Don Alberto",
          "peso_jinete": "4",
          "jinete": "F. Olivares.",
          "preparador": "Marcos Contreras",
          "stud": "Guerrero De La Vida",
          "dividendo": "7.0"
        },
        {
          "lugar": "2",
          "numero": "16",
          "ejemplar": "Mind the Gap",
          "padrillo": "Until Sundown",
          "edad": "",
          "peso_ejemplar": "",
          "distancia": "Haras Matriarca",
          "peso_jinete": "8",
          "jinete": "J. Miño.",
          "preparador": "William Ara",
          "stud": "William Ara D.",
          "dividendo": "18.7"
        },
        {
          "lugar": "3",
          "numero": "13",
          "ejemplar": "Princesitacami",
          "padrillo": "Fortify",
          "edad": "",
          "peso_ejemplar": "",
          "distancia": "Haras Los Turfistas",
          "peso_jinete": "6",
          "jinete": "C. Urbina.",
          "preparador": "Victor Moris L.",
          "stud": "JS",
          "dividendo": "7.5"
        },
        {
          "lugar": "4",
          "numero": "10",
          "ejemplar": "El Espia",
          "padrillo": "Competitive Edge",
          "edad": "",
          "peso_ejemplar": "",
          "distancia": "Haras Convento Viejo",
          "peso_jinete": "6",
          "jinete": "M. Donoso.",
          "preparador": "Juan R. García V.",
          "stud": "Don Salvador",
          "dividendo": "5.9"
        },
        {
          "lugar": "5",
          "numero": "12",
          "ejemplar": "Maxximus",
          "padrillo": "Newfoundland",
          "edad": "",
          "peso_ejemplar": "",
          "distancia": "Haras Dadinco",
          "peso_jinete": "13",
          "jinete": "I. Villagrán.",
          "preparador": "Luis Valdivia B.",
          "stud": "Toleo Toleo",
          "dividendo": "10.6"
        },
        {
          "lugar": "6",
          "numero": "5",
          "ejemplar": "Big Wallace",
          "padrillo": "Hurricane Cat",
          "edad": "",
          "peso_ejemplar": "",
          "distancia": "Haras El Chañar",
          "peso_jinete": "7",
          "jinete": "G. Rodríguez.",
          "preparador": "Braulio Gómez A.",
          "stud": "J.J.",
          "dividendo": "3.1"
        },
        {
          "lugar": "7",
          "numero": "8",
          "ejemplar": "Tanytus",
          "padrillo": "Exaggerator",
          "edad": "",
          "peso_ejemplar": "",
          "distancia": "Haras Mocito Guapo",
          "peso_jinete": "4",
          "jinete": "G. Pérez.",
          "preparador": "Victor Caballeria",
          "stud": "Tata Nacho",
          "dividendo": "3.6"
        },
        {
          "lugar": "8",
          "numero": "9",
          "ejemplar": "Guerrero Arabe",
          "padrillo": "Arabian Spirit",
          "edad": "",
          "peso_ejemplar": "",
          "distancia": "Haras Sumaya",
          "peso_jinete": "3",
          "jinete": "A. Alvarez.",
          "preparador": "Eduardo Donoso",
          "stud": "Los Nanitos",
          "dividendo": "12.1"
        },
        {
          "lugar": "9",
          "numero": "15",
          "ejemplar": "Yipssi Sayen",
          "padrillo": "Court Vision",
          "edad": "",
          "peso_ejemplar": "",
          "distancia": "Haras Villa Rosa",
          "peso_jinete": "9",
          "jinete": "R. Fuenzalida.",
          "preparador": "Victor Moris L.",
          "stud": "El Tirol",
          "dividendo": "55.3"
        },
        {
          "lugar": "10",
          "numero": "7",
          "ejemplar": "Mujer De Pasarela",
          "padrillo": "Mendelssohn",
          "edad": "",
          "peso_ejemplar": "",
          "distancia": "Haras Don Alberto",
          "peso_jinete": "3",
          "jinete": "S. González.",
          "preparador": "Máximo Silva D.",
          "stud": "Maximo Silva D.",
          "dividendo": "26.5"
        },
        {
          "lugar": "11",
          "numero": "1",
          "ejemplar": "Narcisista",
          "padrillo": "Strong Mandate",
          "edad": "",
          "peso_ejemplar": "",
          "distancia": "Haras Dadinco",
          "peso_jinete": "9",
          "jinete": "J. Castillo.",
          "preparador": "Wilfredo Mancilla D.",
          "stud": "French Fries",
          "dividendo": "16.5"
        },
        {
          "lugar": "12",
          "numero": "6",
          "ejemplar": "Guerrero Tenaz",
          "padrillo": "Dylan Thomas",
          "edad": "",
          "peso_ejemplar": "",
          "distancia": "Haras Don Alberto",
          "peso_jinete": "4",
          "jinete": "S. González.",
          "preparador": "Eduardo Donoso",
          "stud": "D`bolton",
          "dividendo": "135.5"
        },
        {
          "lugar": "13",
          "numero": "3",
          "ejemplar": "No Mires Atras",
          "padrillo": "Star Dabbler",
          "edad": "",
          "peso_ejemplar": "",
          "distancia": "Claudio Saide Abusleme",
          "peso_jinete": "4",
          "jinete": "M. Gutiérrez.",
          "preparador": "Cristobal Gonzalez M.",
          "stud": "Tata Chago",
          "dividendo": "34.9"
        }
      ]
    },
    {
      "nro_carrera": "9",
      "premio": "\"Halofresca\"\tBolsa de Premios: CLP $1.822.500\t1100m",
      "resultados": [
        {
          "lugar": "1",
          "numero": "8",
          "ejemplar": "Salus",
          "padrillo": "Empire Maker",
          "edad": "",
          "peso_ejemplar": "",
          "distancia": "Haras Don Alberto",
          "peso_jinete": "7",
          "jinete": "F. Olivares.",
          "preparador": "Marcos Contreras",
          "stud": "Guerrero De La Vida",
          "dividendo": "15.4"
        },
        {
          "lugar": "2",
          "numero": "10",
          "ejemplar": "Louving",
          "padrillo": "Mendelssohn",
          "edad": "",
          "peso_ejemplar": "",
          "distancia": "Haras Don Alberto",
          "peso_jinete": "4",
          "jinete": "S. González.",
          "preparador": "Victor Caballeria",
          "stud": "Tata Nacho",
          "dividendo": "2.5"
        },
        {
          "lugar": "3",
          "numero": "5",
          "ejemplar": "Imperio Babilonico",
          "padrillo": "Classic Empire",
          "edad": "",
          "peso_ejemplar": "",
          "distancia": "Haras Las Camelias",
          "peso_jinete": "4",
          "jinete": "C. Urbina.",
          "preparador": "Victor Moris L.",
          "stud": "A Lo Caballero",
          "dividendo": "7.3"
        },
        {
          "lugar": "4",
          "numero": "7",
          "ejemplar": "One Vision",
          "padrillo": "Gemologist",
          "edad": "",
          "peso_ejemplar": "",
          "distancia": "Haras Santa Olga",
          "peso_jinete": "6",
          "jinete": "J. Medina.",
          "preparador": "Wilfredo Mancilla D.",
          "stud": "Hap",
          "dividendo": "6.7"
        },
        {
          "lugar": "5",
          "numero": "6",
          "ejemplar": "Luiverar",
          "padrillo": "Viscount Nelson",
          "edad": "",
          "peso_ejemplar": "",
          "distancia": "Haras Don Alberto",
          "peso_jinete": "7",
          "jinete": "S. González.",
          "preparador": "Braulio Gómez A.",
          "stud": "Tararira",
          "dividendo": "24.4"
        },
        {
          "lugar": "6",
          "numero": "11",
          "ejemplar": "Green Dress",
          "padrillo": "Lemon Sour",
          "edad": "",
          "peso_ejemplar": "",
          "distancia": "Haras Habib Al Medina",
          "peso_jinete": "4",
          "jinete": "J. Castillo.",
          "preparador": "Eduardo Donoso",
          "stud": "Los Nanitos",
          "dividendo": "6.1"
        },
        {
          "lugar": "7",
          "numero": "2",
          "ejemplar": "Bone Less",
          "padrillo": "Newfoundland",
          "edad": "",
          "peso_ejemplar": "",
          "distancia": "Haras Sumaya",
          "peso_jinete": "8",
          "jinete": "G. Rodríguez.",
          "preparador": "Juan Belzu O.",
          "stud": "Mayfer Y Tata Pato",
          "dividendo": "3.8"
        },
        {
          "lugar": "8",
          "numero": "13",
          "ejemplar": "Valkyria Bliz",
          "padrillo": "Imperia II",
          "edad": "",
          "peso_ejemplar": "",
          "distancia": "Criadero Don Vicente",
          "peso_jinete": "4",
          "jinete": "I. Villagrán.",
          "preparador": "Jorge Araneda M.",
          "stud": "Pompita",
          "dividendo": "15.2"
        },
        {
          "lugar": "9",
          "numero": "3",
          "ejemplar": "Rubio Alocado",
          "padrillo": "Cumpleaños Feliz",
          "edad": "",
          "peso_ejemplar": "",
          "distancia": "Luis Eugenio Gana",
          "peso_jinete": "7",
          "jinete": "W. Quinteros.",
          "preparador": "Jorge Araneda M.",
          "stud": "Renita",
          "dividendo": "22.3"
        },
        {
          "lugar": "10",
          "numero": "1",
          "ejemplar": "Poor Smell",
          "padrillo": "Ivan Denisovich",
          "edad": "",
          "peso_ejemplar": "",
          "distancia": "Haras Don Alberto",
          "peso_jinete": "3",
          "jinete": "R. Fuenzalida.",
          "preparador": "Máximo Silva D.",
          "stud": "Maximo Silva D.",
          "dividendo": "27.5"
        },
        {
          "lugar": "11",
          "numero": "9",
          "ejemplar": "Bapkiza",
          "padrillo": "Cloud Computing",
          "edad": "",
          "peso_ejemplar": "",
          "distancia": "Haras Porta Pía",
          "peso_jinete": "5",
          "jinete": "C. Poblete.",
          "preparador": "Juan Belzu O.",
          "stud": "Milena",
          "dividendo": "14.7"
        }
      ]
    },
    {
      "nro_carrera": "10",
      "premio": "\"Hashimaki\"\tBolsa de Premios: CLP $1.890.000\t1100m",
      "resultados": [
        {
          "lugar": "1",
          "numero": "7",
          "ejemplar": "Alives",
          "padrillo": "Easing Along",
          "edad": "",
          "peso_ejemplar": "",
          "distancia": "Haras Matriarca",
          "peso_jinete": "7",
          "jinete": "J. Miño.",
          "preparador": "William Ara",
          "stud": "William Ara D.",
          "dividendo": "21.4"
        },
        {
          "lugar": "2",
          "numero": "8",
          "ejemplar": "Kwin",
          "padrillo": "Ivan Denisovich",
          "edad": "",
          "peso_ejemplar": "",
          "distancia": "Haras Don Alberto",
          "peso_jinete": "5",
          "jinete": "G. Rodríguez.",
          "preparador": "Victor Caballeria",
          "stud": "Tata Nacho",
          "dividendo": "2.6"
        },
        {
          "lugar": "3",
          "numero": "6",
          "ejemplar": "Veleta De Proa",
          "padrillo": "Palm Springs",
          "edad": "",
          "peso_ejemplar": "",
          "distancia": "Eduardo Garcia Barrio",
          "peso_jinete": "3",
          "jinete": "K. Espina.",
          "preparador": "Rafael Bernal T.",
          "stud": "Cinerarias",
          "dividendo": "6.5"
        },
        {
          "lugar": "4",
          "numero": "12",
          "ejemplar": "Dale Flaca",
          "padrillo": "Hinz",
          "edad": "",
          "peso_ejemplar": "",
          "distancia": "Haras Bucarest",
          "peso_jinete": "3",
          "jinete": "R. Fuenzalida.",
          "preparador": "Eduardo Donoso",
          "stud": "Los Nanitos",
          "dividendo": "6.1"
        },
        {
          "lugar": "5",
          "numero": "2",
          "ejemplar": "Gonsara",
          "padrillo": "Lookin At Lucky",
          "edad": "",
          "peso_ejemplar": "",
          "distancia": "Haras Don Alberto",
          "peso_jinete": "6",
          "jinete": "J. Medina.",
          "preparador": "Carlos Vásquez P.",
          "stud": "Doña Sofía",
          "dividendo": "3.4"
        },
        {
          "lugar": "6",
          "numero": "9",
          "ejemplar": "Soraila",
          "padrillo": "Exaggerator",
          "edad": "",
          "peso_ejemplar": "",
          "distancia": "Haras Doña Icha",
          "peso_jinete": "6",
          "jinete": "F. Moreno.",
          "preparador": "Gabriel Reyes I.",
          "stud": "Palestina",
          "dividendo": "67.6"
        },
        {
          "lugar": "7",
          "numero": "5",
          "ejemplar": "Gran Verraco",
          "padrillo": "Verrazano",
          "edad": "",
          "peso_ejemplar": "",
          "distancia": "Haras Matriarca",
          "peso_jinete": "7",
          "jinete": "I. Villagrán.",
          "preparador": "Gabriel Reyes I.",
          "stud": "Tio Pito",
          "dividendo": "45.8"
        },
        {
          "lugar": "8",
          "numero": "10",
          "ejemplar": "Lucky Storm",
          "padrillo": "California Chrome",
          "edad": "",
          "peso_ejemplar": "",
          "distancia": "Haras Sumaya",
          "peso_jinete": "6",
          "jinete": "C. Urbina.",
          "preparador": "Victor Moris L.",
          "stud": "Aleph",
          "dividendo": "7.9"
        },
        {
          "lugar": "9",
          "numero": "11",
          "ejemplar": "By Tintinella",
          "padrillo": "Quick Casablanca",
          "edad": "",
          "peso_ejemplar": "",
          "distancia": "Benedicto Pierola V.",
          "peso_jinete": "4",
          "jinete": "J. Villagran.",
          "preparador": "Victor Moris L.",
          "stud": "Los Pierola",
          "dividendo": "27.8"
        },
        {
          "lugar": "10",
          "numero": "3",
          "ejemplar": "Ejemplo De Valor",
          "padrillo": "Lookin At Lucky",
          "edad": "",
          "peso_ejemplar": "",
          "distancia": "Haras Don Alberto",
          "peso_jinete": "6",
          "jinete": "G. Pérez.",
          "preparador": "Marcos Contreras",
          "stud": "Guerrero De La Vida",
          "dividendo": "10.7"
        },
        {
          "lugar": "11",
          "numero": "13",
          "ejemplar": "Madame Cayetana",
          "padrillo": "Dangerous Midge",
          "edad": "",
          "peso_ejemplar": "",
          "distancia": "Haras Chevalex",
          "peso_jinete": "4",
          "jinete": "J. Cueto.",
          "preparador": "Wilfredo Mancilla D.",
          "stud": "Wilfredo Mancilla D.",
          "dividendo": "19.7"
        },
        {
          "lugar": "12",
          "numero": "4",
          "ejemplar": "Pasion Por Ella",
          "padrillo": "Flyer",
          "edad": "",
          "peso_ejemplar": "",
          "distancia": "Haras Viejo Perro",
          "peso_jinete": "4",
          "jinete": "M. Gutiérrez.",
          "preparador": "Cristobal Gonzalez M.",
          "stud": "Verónica Morales O.",
          "dividendo": "30.2"
        }
      ]
    }
  ]
}