{
  "id_reunion": "97806",
  "id_pais": 1,
  "numero_reunion": "78",
  "fecha_reunion": "2025-12-24",
  "fecha_reunion_real": "Miércoles 24 de Diciembre del año 2025",
  "director_turno": "Sr. Mauricio Maurel T.",
  "id_hipodromo": 4,
  "nombre_hipodromo": "Valparaíso Sporting",
  "abreviatura_hipodromo": "VSC",
  "abreviatura_hipodromo_corta": "V",
  "signo_moneda": "CLP $",
  "signo_moneda_puro": "CLP",
  "reunion_calculada": false,
  "reunion_resultados": true,
  "pronosticos_habilitados": 2002,
  "logo_hipodromo": "logo_vsc.gif",
  "pais_hipodromo": "Chile",
  "ciudad_hipodromo": "Viña del Mar",
  "reunion_equineline": "0",
  "primera_carrera": {
    "id_carrera": "792554",
    "nro": "1",
    "hora": "13:00"
  },
  "carreras": [
    {
      "id_reunion": "97806",
      "id_carrera": "792554",
      "correlativo": "1",
      "id_pais": "1",
      "hora_carrera": "13:00",
      "nombre_premio": "Tango Bar",
      "premio1": "1.300.000",
      "signo_moneda": "CLP $",
      "signo_moneda_puro": "CLP",
      "es_clasico": false,
      "liberado": true,
      "resultado": true,
      "calculo": true,
      "anulada_suspendida": "",
      "videos": "videos_vsc",
      "id_tipo_carrera": "2",
      "tipo_carrera": "Handicap",
      "abreviatura_tipo_carrera": "Hd",
      "id_grupo": null,
      "grupo": null,
      "id_indice": "440",
      "indice": "1",
      "id_distancia": "4",
      "distancia": "1100",
      "id_condicion": "13",
      "condicion": "Caballos 3 años y más",
      "abreviatura_condicion": "3a+",
      "multimedia": {
        "pdf": false,
        "fotos": false,
        "video": "kU7VSKKRkGk"
      },
      "primeros": []
    },
    {
      "id_reunion": "97806",
      "id_carrera": "792555",
      "correlativo": "2",
      "id_pais": "1",
      "hora_carrera": "13:28",
      "nombre_premio": "Troyano",
      "premio1": "1.400.000",
      "signo_moneda": "CLP $",
      "signo_moneda_puro": "CLP",
      "es_clasico": false,
      "liberado": true,
      "resultado": true,
      "calculo": true,
      "anulada_suspendida": "",
      "videos": "videos_vsc",
      "id_tipo_carrera": "1",
      "tipo_carrera": "Condicional",
      "abreviatura_tipo_carrera": "Cd",
      "id_grupo": null,
      "grupo": null,
      "id_indice": null,
      "indice": null,
      "id_distancia": "4",
      "distancia": "1100",
      "id_condicion": "17",
      "condicion": "Machos 3 años no ganadores",
      "abreviatura_condicion": "m3ap",
      "multimedia": {
        "pdf": false,
        "fotos": false,
        "video": "LfPNDJOkH8w"
      },
      "primeros": []
    },
    {
      "id_reunion": "97806",
      "id_carrera": "792556",
      "correlativo": "3",
      "id_pais": "1",
      "hora_carrera": "13:56",
      "nombre_premio": "Tutto Azul",
      "premio1": "1.350.000",
      "signo_moneda": "CLP $",
      "signo_moneda_puro": "CLP",
      "es_clasico": false,
      "liberado": true,
      "resultado": true,
      "calculo": true,
      "anulada_suspendida": "",
      "videos": "videos_vsc",
      "id_tipo_carrera": "2",
      "tipo_carrera": "Handicap",
      "abreviatura_tipo_carrera": "Hd",
      "id_grupo": null,
      "grupo": null,
      "id_indice": "554",
      "indice": "2",
      "id_distancia": "4",
      "distancia": "1100",
      "id_condicion": "13",
      "condicion": "Caballos 3 años y más",
      "abreviatura_condicion": "3a+",
      "multimedia": {
        "pdf": false,
        "fotos": false,
        "video": "1iO5B5IDtjA"
      },
      "primeros": []
    },
    {
      "id_reunion": "97806",
      "id_carrera": "792557",
      "correlativo": "4",
      "id_pais": "1",
      "hora_carrera": "14:24",
      "nombre_premio": "Tonino",
      "premio1": "1.400.000",
      "signo_moneda": "CLP $",
      "signo_moneda_puro": "CLP",
      "es_clasico": false,
      "liberado": true,
      "resultado": true,
      "calculo": true,
      "anulada_suspendida": "",
      "videos": "videos_vsc",
      "id_tipo_carrera": "1",
      "tipo_carrera": "Condicional",
      "abreviatura_tipo_carrera": "Cd",
      "id_grupo": null,
      "grupo": null,
      "id_indice": null,
      "indice": null,
      "id_distancia": "4",
      "distancia": "1100",
      "id_condicion": "17",
      "condicion": "Machos 3 años no ganadores",
      "abreviatura_condicion": "m3ap",
      "multimedia": {
        "pdf": false,
        "fotos": false,
        "video": "VzSggovV3B0"
      },
      "primeros": []
    },
    {
      "id_reunion": "97806",
      "id_carrera": "792558",
      "correlativo": "5",
      "id_pais": "1",
      "hora_carrera": "14:52",
      "nombre_premio": "Tacua",
      "premio1": "1.500.000",
      "signo_moneda": "CLP $",
      "signo_moneda_puro": "CLP",
      "es_clasico": false,
      "liberado": true,
      "resultado": true,
      "calculo": true,
      "anulada_suspendida": "",
      "videos": "videos_vsc",
      "id_tipo_carrera": "2",
      "tipo_carrera": "Handicap",
      "abreviatura_tipo_carrera": "Hd",
      "id_grupo": null,
      "grupo": null,
      "id_indice": "184",
      "indice": "11 al 6",
      "id_distancia": "5",
      "distancia": "1200",
      "id_condicion": "13",
      "condicion": "Caballos 3 años y más",
      "abreviatura_condicion": "3a+",
      "multimedia": {
        "pdf": false,
        "fotos": false,
        "video": "sc4PKjOdzb4"
      },
      "primeros": []
    },
    {
      "id_reunion": "97806",
      "id_carrera": "792560",
      "correlativo": "6",
      "id_pais": "1",
      "hora_carrera": "15:20",
      "nombre_premio": "Tiberio",
      "premio1": "1.350.000",
      "signo_moneda": "CLP $",
      "signo_moneda_puro": "CLP",
      "es_clasico": false,
      "liberado": true,
      "resultado": true,
      "calculo": true,
      "anulada_suspendida": "",
      "videos": "videos_vsc",
      "id_tipo_carrera": "2",
      "tipo_carrera": "Handicap",
      "abreviatura_tipo_carrera": "Hd",
      "id_grupo": null,
      "grupo": null,
      "id_indice": "25",
      "indice": "4 al 3",
      "id_distancia": "4",
      "distancia": "1100",
      "id_condicion": "13",
      "condicion": "Caballos 3 años y más",
      "abreviatura_condicion": "3a+",
      "multimedia": {
        "pdf": false,
        "fotos": false,
        "video": "iobfh9QWdgY"
      },
      "primeros": []
    },
    {
      "id_reunion": "97806",
      "id_carrera": "792561",
      "correlativo": "7",
      "id_pais": "1",
      "hora_carrera": "15:48",
      "nombre_premio": "Taitonto",
      "premio1": "1.300.000",
      "signo_moneda": "CLP $",
      "signo_moneda_puro": "CLP",
      "es_clasico": false,
      "liberado": true,
      "resultado": true,
      "calculo": true,
      "anulada_suspendida": "",
      "videos": "videos_vsc",
      "id_tipo_carrera": "2",
      "tipo_carrera": "Handicap",
      "abreviatura_tipo_carrera": "Hd",
      "id_grupo": null,
      "grupo": null,
      "id_indice": "440",
      "indice": "1",
      "id_distancia": "4",
      "distancia": "1100",
      "id_condicion": "13",
      "condicion": "Caballos 3 años y más",
      "abreviatura_condicion": "3a+",
      "multimedia": {
        "pdf": false,
        "fotos": false,
        "video": "OKkdBczF-JM"
      },
      "primeros": []
    },
    {
      "id_reunion": "97806",
      "id_carrera": "792563",
      "correlativo": "8",
      "id_pais": "1",
      "hora_carrera": "16:16",
      "nombre_premio": "Two Airs",
      "premio1": "1.500.000",
      "signo_moneda": "CLP $",
      "signo_moneda_puro": "CLP",
      "es_clasico": false,
      "liberado": true,
      "resultado": true,
      "calculo": true,
      "anulada_suspendida": "",
      "videos": "videos_vsc",
      "id_tipo_carrera": "2",
      "tipo_carrera": "Handicap",
      "abreviatura_tipo_carrera": "Hd",
      "id_grupo": null,
      "grupo": null,
      "id_indice": "22",
      "indice": "19 al 15",
      "id_distancia": "4",
      "distancia": "1100",
      "id_condicion": "13",
      "condicion": "Caballos 3 años y más",
      "abreviatura_condicion": "3a+",
      "multimedia": {
        "pdf": false,
        "fotos": false,
        "video": "-afIYnj3ELA"
      },
      "primeros": []
    },
    {
      "id_reunion": "97806",
      "id_carrera": "792564",
      "correlativo": "9",
      "id_pais": "1",
      "hora_carrera": "16:44",
      "nombre_premio": "Navidad",
      "premio1": "2.300.000",
      "signo_moneda": "CLP $",
      "signo_moneda_puro": "CLP",
      "es_clasico": true,
      "liberado": true,
      "resultado": true,
      "calculo": true,
      "anulada_suspendida": "",
      "videos": "videos_vsc",
      "id_tipo_carrera": "8",
      "tipo_carrera": "Clásico",
      "abreviatura_tipo_carrera": "Cl",
      "id_grupo": "12",
      "grupo": "ClCd",
      "id_indice": null,
      "indice": null,
      "id_distancia": "6",
      "distancia": "1300",
      "id_condicion": "40",
      "condicion": "Machos y Hembras 3 años ganadores",
      "abreviatura_condicion": "3ag",
      "multimedia": {
        "pdf": false,
        "fotos": false,
        "video": "mr9N7OLy3xQ"
      },
      "primeros": []
    },
    {
      "id_reunion": "97806",
      "id_carrera": "792566",
      "correlativo": "10",
      "id_pais": "1",
      "hora_carrera": "17:12",
      "nombre_premio": "Tapadita",
      "premio1": "1.600.000",
      "signo_moneda": "CLP $",
      "signo_moneda_puro": "CLP",
      "es_clasico": false,
      "liberado": true,
      "resultado": true,
      "calculo": true,
      "anulada_suspendida": "",
      "videos": "videos_vsc",
      "id_tipo_carrera": "2",
      "tipo_carrera": "Handicap",
      "abreviatura_tipo_carrera": "Hd",
      "id_grupo": null,
      "grupo": null,
      "id_indice": "378",
      "indice": "34 al 23",
      "id_distancia": "4",
      "distancia": "1100",
      "id_condicion": "13",
      "condicion": "Caballos 3 años y más",
      "abreviatura_condicion": "3a+",
      "multimedia": {
        "pdf": false,
        "fotos": false,
        "video": "LKSvVm9fZRo"
      },
      "primeros": []
    },
    {
      "id_reunion": "97806",
      "id_carrera": "792567",
      "correlativo": "11",
      "id_pais": "1",
      "hora_carrera": "17:40",
      "nombre_premio": "Trebol Rojo",
      "premio1": "1.400.000",
      "signo_moneda": "CLP $",
      "signo_moneda_puro": "CLP",
      "es_clasico": false,
      "liberado": true,
      "resultado": true,
      "calculo": true,
      "anulada_suspendida": "",
      "videos": "videos_vsc",
      "id_tipo_carrera": "2",
      "tipo_carrera": "Handicap",
      "abreviatura_tipo_carrera": "Hd",
      "id_grupo": null,
      "grupo": null,
      "id_indice": "36",
      "indice": "9 al 7",
      "id_distancia": "4",
      "distancia": "1100",
      "id_condicion": "13",
      "condicion": "Caballos 3 años y más",
      "abreviatura_condicion": "3a+",
      "multimedia": {
        "pdf": false,
        "fotos": false,
        "video": "HLNP9qV1Kuk"
      },
      "primeros": []
    },
    {
      "id_reunion": "97806",
      "id_carrera": "792568",
      "correlativo": "12",
      "id_pais": "1",
      "hora_carrera": "18:10",
      "nombre_premio": "Toro Negro",
      "premio1": "1.450.000",
      "signo_moneda": "CLP $",
      "signo_moneda_puro": "CLP",
      "es_clasico": false,
      "liberado": true,
      "resultado": true,
      "calculo": true,
      "anulada_suspendida": "",
      "videos": "videos_vsc",
      "id_tipo_carrera": "2",
      "tipo_carrera": "Handicap",
      "abreviatura_tipo_carrera": "Hd",
      "id_grupo": null,
      "grupo": null,
      "id_indice": "77",
      "indice": "11 al 9",
      "id_distancia": "4",
      "distancia": "1100",
      "id_condicion": "13",
      "condicion": "Caballos 3 años y más",
      "abreviatura_condicion": "3a+",
      "multimedia": {
        "pdf": false,
        "fotos": false,
        "video": "gpWd3Oj_ugw"
      },
      "primeros": []
    },
    {
      "id_reunion": "97806",
      "id_carrera": "792569",
      "correlativo": "13",
      "id_pais": "1",
      "hora_carrera": "18:40",
      "nombre_premio": "Tan Bueno",
      "premio1": "1.450.000",
      "signo_moneda": "CLP $",
      "signo_moneda_puro": "CLP",
      "es_clasico": false,
      "liberado": true,
      "resultado": true,
      "calculo": true,
      "anulada_suspendida": "",
      "videos": "videos_vsc",
      "id_tipo_carrera": "2",
      "tipo_carrera": "Handicap",
      "abreviatura_tipo_carrera": "Hd",
      "id_grupo": null,
      "grupo": null,
      "id_indice": "41",
      "indice": "14 al 12",
      "id_distancia": "4",
      "distancia": "1100",
      "id_condicion": "13",
      "condicion": "Caballos 3 años y más",
      "abreviatura_condicion": "3a+",
      "multimedia": {
        "pdf": false,
        "fotos": false,
        "video": "lS-R0q3R9LE"
      },
      "primeros": []
    },
    {
      "id_reunion": "97806",
      "id_carrera": "792570",
      "correlativo": "14",
      "id_pais": "1",
      "hora_carrera": "19:10",
      "nombre_premio": "Taifun",
      "premio1": "1.350.000",
      "signo_moneda": "CLP $",
      "signo_moneda_puro": "CLP",
      "es_clasico": false,
      "liberado": true,
      "resultado": true,
      "calculo": true,
      "anulada_suspendida": "",
      "videos": "videos_vsc",
      "id_tipo_carrera": "2",
      "tipo_carrera": "Handicap",
      "abreviatura_tipo_carrera": "Hd",
      "id_grupo": null,
      "grupo": null,
      "id_indice": "136",
      "indice": "6 al 5",
      "id_distancia": "4",
      "distancia": "1100",
      "id_condicion": "13",
      "condicion": "Caballos 3 años y más",
      "abreviatura_condicion": "3a+",
      "multimedia": {
        "pdf": false,
        "fotos": false,
        "video": false
      },
      "primeros": []
    }
  ],
  "pdf_elturf": {
    "existe": true,
    "url": "pdf-programa-elturf?id_reunion=97806",
    "lugar_pdf": "lista_reuniones"
  },
  "pdf_otros": {
    "pdf": false,
    "pdf_sorteo_partidas": {
      "existe": false,
      "url": false
    },
    "pdf_cartas": {
      "existe": false,
      "url": false
    },
    "pdf_inscripciones": {
      "existe": false,
      "url": false
    },
    "pdf_programas": {
      "existe": false,
      "url": false
    },
    "pdf_volantes": {
      "existe": false,
      "url": false
    },
    "pdf_novedades": {
      "existe": false,
      "url": false
    },
    "pdf_modificaciones": {
      "existe": false,
      "url": false
    },
    "pdf_actas": {
      "existe": false,
      "url": false
    },
    "pdf_doping": {
      "existe": false,
      "url": false
    }
  },
  "pdf": {
    "elturf": {
      "existe": true,
      "url": "pdf-programa-elturf?id_reunion=97806"
    },
    "dlh": {
      "existe": false,
      "url": false
    }
  },
  "menu_reunion": {
    "pronosticos": true,
    "pronosticos_elturf": true,
    "pronosticos_prensa": true,
    "novedades": true,
    "novedades_retiros": true,
    "novedades_repetidos": true,
    "novedades_cambios_preparadores": true,
    "novedades_cambios_studs": true
  }
}